pyccup/core.py
pyccup/element.py
pyccup/elems.py
pyccup/page.py
pyccup-0.0.3.dist-info/licenses/LICENSE
pyccup-0.0.3.dist-info/METADATA
pyccup-0.0.3.dist-info/WHEEL
pyccup-0.0.3.dist-info/top_level.txt
pyccup-0.0.3.dist-info/RECORD
