Metadata-Version: 2.4
Name: pyccup
Version: 0.0.3
Summary: A derivation of Nicolas Bessi's trivial port of Hiccup to Python
Author-email: Nicolas Bessi <nbessi@gmail.com>, inaimathi <leo.zovic@gmail.com>
Project-URL: Homepage, https://github.com/inaimathi/pyccup
Project-URL: Issues, https://github.com/inaimathi/pyccup/issues
Classifier: Programming Language :: Python
Classifier: License :: OSI Approved :: GNU Affero General Public License v3
Classifier: Operating System :: OS Independent
Requires-Python: >=3.4
License-File: LICENSE
Dynamic: license-file
